{"cameraMode":{"drawMode":0,"name":"Shaded","section":"Shading Mode"},"sceneLighting":true,"audioPlay":false,"sceneViewState":{"m_AlwaysRefresh":false,"showFog":true,"showSkybox":true,"showFlares":true,"showImageEffects":true,"showParticleSystems":true,"showVisualEffectGraphs":true,"m_FxEnabled":true},"in2DMode":false,"pivot":{"x":-0.18605780601501466,"y":3.5842180252075197,"z":0.9293633699417114},"rotation":{"x":-0.020839549601078035,"y":0.5378898978233337,"z":0.015370473265647889,"w":0.8426527976989746},"size":1.7118682861328126,"orthographic":false}